yaseen_fist_capstone_10k/__init__.py
yaseen_fist_capstone_10k/main.py
yaseen_DataPrepKit-0.1.0.dist-info/METADATA
yaseen_DataPrepKit-0.1.0.dist-info/WHEEL
yaseen_DataPrepKit-0.1.0.dist-info/top_level.txt
yaseen_DataPrepKit-0.1.0.dist-info/RECORD
