Metadata-Version: 2.1
Name: yaseen_DataPrepKit
Version: 0.1.0
Summary: A python code that can read two csv and json files and has some functionality for missing values and can give summary and encoding for the values
Author: Yaseen Mohammed
Author-email: yasien202020@gmail.com
Classifier: Programming Language :: Python :: 3.12
Classifier: License :: OSI Approved :: MIT License
Classifier: Operating System :: OS Independent
Requires-Python: >=3.6
